auth0_client/Auth0Client.py
auth0_client/__init__.py
auth0_client/cli_util.py
auth0_client/command.py
auth0_client/config.py
auth0_client/commands/__init__.py
auth0_client/commands/administration.py
auth0_client/commands/blacklists.py
auth0_client/commands/client_grants.py
auth0_client/commands/clients.py
auth0_client/commands/connections.py
auth0_client/commands/custom_domains.py
auth0_client/commands/device_credentials.py
auth0_client/commands/email_templates.py
auth0_client/commands/emails.py
auth0_client/commands/grants.py
auth0_client/commands/guardian.py
auth0_client/commands/jobs.py
auth0_client/commands/logs.py
auth0_client/commands/resource_servers.py
auth0_client/commands/rules.py
auth0_client/commands/rules_config.py
auth0_client/commands/stats.py
auth0_client/commands/tenants.py
auth0_client/commands/tickets.py
auth0_client/commands/user_blocks.py
auth0_client/commands/users.py
auth0_client/commands/users_by_email.py
auth0_client/menu/__init__.py
auth0_client/menu/auth_menu.py
auth0_client/menu/exceptions.py
auth0_client/menu/backported/__init__.py
auth0_client/menu/backported/inspect2.py
auth0_client/menu/commons/__init__.py
auth0_client/menu/commons/case_class.py
auth0_client/menu/commons/collection.py
auth0_client/menu/commons/command.py
auth0_client/menu/commons/functional.py
auth0_client/menu/commons/io.py
auth0_client/menu/commons/string.py
auth0_client/menu/commons/terminal.py
auth0_client/menu/commons/types.py
auth0_client/menu/commons/unittest.py
auth0_client/menu/controller/__init__.py
auth0_client/menu/controller/command_executor.py
auth0_client/menu/controller/executor.py
auth0_client/menu/datafiles/auth-menu.yml
auth0_client/menu/datafiles/scripts/blacklist_a_token.py
auth0_client/menu/datafiles/scripts/configure_email_provider.py
auth0_client/menu/datafiles/scripts/create_an_email_template.py
auth0_client/menu/datafiles/scripts/create_email_verification_ticket.py
auth0_client/menu/datafiles/scripts/create_guardian_enrollment_ticket.py
auth0_client-0.6.1.dist-info/LICENSE
auth0_client-0.6.1.dist-info/METADATA
auth0_client-0.6.1.dist-info/WHEEL
auth0_client-0.6.1.dist-info/entry_points.txt
auth0_client-0.6.1.dist-info/top_level.txt
auth0_client-0.6.1.dist-info/RECORD
