Metadata-Version: 2.1
Name: auth0-client
Version: 0.6.1
Summary: auth0 click client.
Home-page: https://github.com/rubelw/auth0_client
Author: Will Rubel
Author-email: willrubel@gmail.com
License: UNKNOWN
Keywords: auth0,client
Platform: any
Classifier: Development Status :: 4 - Beta
Classifier: Intended Audience :: Developers
Classifier: Natural Language :: English
Classifier: License :: OSI Approved :: MIT License
Classifier: Operating System :: OS Independent
Classifier: Programming Language :: Python
Classifier: Programming Language :: Python
Classifier: Programming Language :: Python :: 2
Classifier: Programming Language :: Python :: 2.6
Classifier: Programming Language :: Python :: 2.7
Classifier: Programming Language :: Python :: 3
Classifier: Programming Language :: Python :: 3.3
Classifier: Programming Language :: Python :: 3.4
Classifier: Programming Language :: Python :: 3.5
Classifier: Programming Language :: Python :: 3.6
Requires-Dist: boto3 (>=1.4.3)
Requires-Dist: requests (>=2.18)
Requires-Dist: Click (>=6.7)
Requires-Dist: configparser (>=3.5.0)
Requires-Dist: future (>=0.16.0)
Requires-Dist: six (>=1.11.0)
Requires-Dist: pip
Requires-Dist: click-help-colors
Requires-Dist: reprint
Requires-Dist: tabulate
Requires-Dist: click-completion
